cfl/__init__.py
cfl/block.py
cfl/dataset.py
cfl/experiment.py
cfl/clustering/Y_given_Xmacro.py
cfl/clustering/__init__.py
cfl/clustering/cause_clusterer.py
cfl/clustering/cluster_tuning_util.py
cfl/clustering/clusterer_model.py
cfl/clustering/effect_clusterer.py
cfl/clustering/snn.py
cfl/cond_density_estimation/__init__.py
cfl/cond_density_estimation/cde_model.py
cfl/cond_density_estimation/condDensityEstimator.py
cfl/cond_density_estimation/condExpBase.py
cfl/cond_density_estimation/condExpCNN.py
cfl/cond_density_estimation/condExpDIY.py
cfl/cond_density_estimation/condExpMod.py
cfl/cond_density_estimation/condExpRidgeRegCV.py
cfl/post_cfl/__init__.py
cfl/post_cfl/intervention_rec.py
cfl/post_cfl/macro_cond_prob.py
cfl/post_cfl/microvariable_importance.py
cfl/post_cfl/post_cfl_util.py
cfl/util/__init__.py
cfl/util/data_processing.py
cfl/util/experiment_loading.py
cfl/util/find_xlbl_locations.py
cfl/util/input_val.py
cfl/visualization/__init__.py
cfl/visualization/basic_visualizations.py
cfl/visualization/cde_diagnostic.py
cfl/visualization/clustering_to_sankey.py
cfl/visualization/data_sample_visualizations.py
visual_bars/__init__.py
visual_bars/generate_visual_bars_data.py
visual_bars/visual_bars_vis.py
cfl-1.3.2.dist-info/LICENSE.txt
cfl-1.3.2.dist-info/METADATA
cfl-1.3.2.dist-info/WHEEL
cfl-1.3.2.dist-info/top_level.txt
cfl-1.3.2.dist-info/RECORD
